<?xml version="1.0" encoding="utf-8" ?><dwsync><file name="gallery_thumb_2.jpg" server="myeekona.com/public_html/" local="3490695718" remote="3501700500" Dst="-1" /><file name="gallery_thumb_1.jpg" server="myeekona.com/public_html/" local="3501902972" remote="3501906600" Dst="-1" /><file name="gallery_thumb_3.jpg" server="myeekona.com/public_html/" local="3490695708" remote="3501700500" Dst="-1" /><file name="gallery_thumb_4.jpg" server="myeekona.com/public_html/" local="3490695696" remote="3501700500" Dst="-1" /><file name="gallery_thumb_5.jpg" server="myeekona.com/public_html/" local="3490695684" remote="3501700500" Dst="-1" /><file name="gallery_thumb_6.jpg" server="myeekona.com/public_html/" local="3490695674" remote="3501700500" Dst="-1" /><file name="gallery_thumb_7.jpg" server="myeekona.com/public_html/" local="3490695662" remote="3501700500" Dst="-1" /><file name="gallery_thumb_8.jpg" server="myeekona.com/public_html/" local="3490695742" remote="3501700500" Dst="-1" /></dwsync>